{
  "generatedAt": "2026-03-03T03:14:20.335Z",
  "base": {
    "name": "nextclaw",
    "projectRoot": "/home/runner/work/nextclaw/nextclaw",
    "scope": {
      "includeDirs": [
        "apps",
        "packages",
        "workers",
        "bridge",
        "scripts"
      ],
      "includeExtensions": [
        ".ts",
        ".tsx",
        ".js",
        ".jsx",
        ".mjs",
        ".cjs",
        ".sh",
        ".yml",
        ".yaml"
      ],
      "excludeDirs": [
        ".git",
        ".changeset",
        "node_modules",
        "dist",
        "coverage",
        "build",
        "ui-dist",
        ".turbo"
      ]
    },
    "totals": {
      "files": 286,
      "totalLines": 48607,
      "blankLines": 5102,
      "commentLines": 271,
      "codeLines": 43234
    }
  },
  "benchmark": {
    "name": "openclaw",
    "projectRoot": "/home/runner/work/nextclaw/nextclaw/external/openclaw",
    "scope": {
      "includeDirs": [
        "src",
        "extensions",
        "scripts"
      ],
      "includeExtensions": [
        ".ts",
        ".tsx",
        ".js",
        ".jsx",
        ".mjs",
        ".cjs",
        ".sh",
        ".yml",
        ".yaml"
      ],
      "excludeDirs": [
        ".git",
        ".changeset",
        "node_modules",
        "dist",
        "coverage",
        "build",
        "ui-dist",
        ".turbo"
      ]
    },
    "totals": {
      "files": 5167,
      "totalLines": 962138,
      "blankLines": 91734,
      "commentLines": 22492,
      "codeLines": 847912
    }
  },
  "comparison": {
    "baseMinusBenchmarkLines": -804678,
    "basePercentOfBenchmark": 5.1,
    "benchmarkMultipleOfBase": 19.61,
    "baseIsLighterByPercent": 94.9
  }
}
